<?xml version="1.0"?>
<block>
  <name>ADS-B Demodulator</name>
  <key>adsb_demod</key>
  <category>[ADS-B]</category>
  <import>import adsb</import>
  <make>adsb.demod($fs)</make>
  <!-- Make one 'param' node for every Parameter you want settable from the GUI.
       Sub-nodes:
       * name
       * key (makes the value accessible as $keyname, e.g. in the make node)
       * type -->
  <param>
    <name>Sampling Rate</name>
    <key>fs</key>
    <type>float</type>
  </param>

  <!-- Make one 'sink' node per input. Sub-nodes:
       * name (an identifier for the GUI)
       * type
       * vlen
       * optional (set to 1 for optional inputs) -->
  <sink>
    <name>in</name>
    <type>float</type>
  </sink>

  <!-- Make one 'source' node per output. Sub-nodes:
       * name (an identifier for the GUI)
       * type
       * vlen
       * optional (set to 1 for optional inputs) -->
  <source>
    <name>pkt</name>
    <type>message</type>
  </source>
  <source>
    <name>out</name>
    <type>float</type>
  </source>
</block>
